{"Title":"A.S.V.","Industry":"CONSTRUCTION MACHINERY \u0026 EQUIP","Employees":"157","Founded":"","Address":"","Phone":"(218) 327-3434","Web_address":"http://www.asvllc.com","Market_cup":"$68.6mil","Revenues":"$103.8 mil (last 12 months)","Net_income":"$-1.2 mil (last 12 months)","Symbol":"ASV","Exchange":"NASDAQ","Shares":"3.8","Price_range":"$7.00 - $7.00","Est_volume":"$26.6 mil","Manager":"Roth Capital Partners","CO_managers":"Seaport Global Securities","Exp_to_trade":"5/12/2017","Status":"","Quiet_period":"Available only to Subscribers","Lock_up_period":"Available only to Subscribers","Scoop_rate":"Available only to Subscribers","Rating_change":"Available only to Subscribers","Business":"We design and manufacture a broad range of high quality compact track loader (“CTL”) and skid steer loader (“SSL”) equipment, marketed through a distribution network in North America, Australia and New Zealand under the ASV and Terex brands. We also serve as a private label original equipment manufacturer for several manufacturers."}