{"Title":"TPG RE Finance Trust","Industry":"REAL ESTATE INVESTMENT TRUST","Employees":"0","Founded":"","Address":"","Phone":"(212) 601-7400","Web_address":"http://www.tpgrefinancetrust.com","Market_cup":"$1189.6mil","Revenues":"$167.8 mil (last 12 months)","Net_income":"$77.2 mil (last 12 months)","Symbol":"TRTX","Exchange":"NYSE","Shares":"11.0","Price_range":"$20.00 - $20.00","Est_volume":"$225.5 mil","Manager":"BofA Merrill Lynch/ Citigroup/ Goldman Sachs/ Wells Fargo Securities/ Deutsche Bank Securities/ J. P. Morgan/ Morgan Stanley/ Barclays","CO_managers":"TPG Capital BD/ JMP Securities","Exp_to_trade":"7/20/2017","Status":"","Quiet_period":"Available only to Subscribers","Lock_up_period":"Available only to Subscribers","Scoop_rate":"Available only to Subscribers","Rating_change":"Available only to Subscribers","Business":"We are a commercial real estate finance company sponsored by TPG. We directly originate, acquire and manage commercial mortgage loans and other commercial real estate-related debt instruments for our balance sheet. Our objective is to provide attractive risk-adjusted returns to our stockholders over time through cash distributions and capital appreciation.As of December 31, 2016, our portfolio consisted of 54 first mortgage loans (or interests therein) with an aggregate unpaid principal balance of $2.4 billion and two mezzanine loans with an aggregate unpaid principal balance of $41.4 million, and collectively having a weighted average credit spread of 5.1%, a weighted average all-in yield of 6.1%, a weighted average extended maturity (assuming all extension options have been exercised by borrowers) of 3.0 years and a weighted average LTV of 58.4%."}